impact_stack/proxyfix/__init__.py
impact_stack_proxyfix-0.1.0.dist-info/licenses/LICENSE
impact_stack_proxyfix-0.1.0.dist-info/METADATA
impact_stack_proxyfix-0.1.0.dist-info/WHEEL
impact_stack_proxyfix-0.1.0.dist-info/top_level.txt
impact_stack_proxyfix-0.1.0.dist-info/RECORD
